isobiscuit/__init__.py
isobiscuit/biasm/__init__.py
isobiscuit/biasm/binify.py
isobiscuit/biasm/codes.py
isobiscuit/biasm/compiler.py
isobiscuit/cli.py
isobiscuit/compiler/__init__.py
isobiscuit/compiler/build.py
isobiscuit/install.py
isobiscuit/installer/__init__.py
isobiscuit/installer/install.py
isobiscuit/run.py
isobiscuit/runner/__init__.py
isobiscuit/runner/engine.py
isobiscuit/runner/magic.py
isobiscuit/runner/parser.py
isobiscuit/runner/reader.py
isobiscuit/runner/runner.py
isobiscuit/runner/runtime.py
isobiscuit-0.3.13.dist-info/LICENSE.txt
isobiscuit-0.3.13.dist-info/METADATA
isobiscuit-0.3.13.dist-info/WHEEL
isobiscuit-0.3.13.dist-info/entry_points.txt
isobiscuit-0.3.13.dist-info/RECORD
