Metadata-Version: 2.1
Name: isobiscuit
Version: 0.3.13
Summary: IsoBiscuit is a tool for virtualize an isolate processes
License: LICENSE.txt
Author: trollmii
Author-email: trollmii@outlook.de
Requires-Python: >=3.12,<4.0
Classifier: License :: Other/Proprietary License
Classifier: Programming Language :: Python :: 3
Classifier: Programming Language :: Python :: 3.12
Classifier: Programming Language :: Python :: 3.13
Requires-Dist: colorama (>=0.4.6,<0.5.0)
Requires-Dist: pyyaml (>=6.0.2,<7.0.0)
Requires-Dist: requests (>=2.0.0,<3.0.0)
